asammdf/__init__.py
asammdf/app/asammdfgui.py
asammdf/blocks/__init__.py
asammdf/blocks/blocks_common.py
asammdf/blocks/bus_logging_utils.py
asammdf/blocks/conversion_utils.py
asammdf/blocks/cutils.c
asammdf/blocks/cutils.pyd
asammdf/blocks/cutils.pyi
asammdf/blocks/mdf_common.py
asammdf/blocks/mdf_v2.py
asammdf/blocks/mdf_v3.py
asammdf/blocks/mdf_v4.py
asammdf/blocks/options.py
asammdf/blocks/source_utils.py
asammdf/blocks/types.py
asammdf/blocks/utils.py
asammdf/blocks/v2_v3_blocks.py
asammdf/blocks/v2_v3_constants.py
asammdf/blocks/v4_blocks.py
asammdf/blocks/v4_constants.py
asammdf/gui/__init__.py
asammdf/gui/dialogs/__init__.py
asammdf/gui/dialogs/advanced_search.py
asammdf/gui/dialogs/advanced_search_helpers.py
asammdf/gui/dialogs/bus_database_manager.py
asammdf/gui/dialogs/channel_group_info.py
asammdf/gui/dialogs/channel_info.py
asammdf/gui/dialogs/conversion_editor.py
asammdf/gui/dialogs/define_channel.py
asammdf/gui/dialogs/dependencies_dlg.py
asammdf/gui/dialogs/error_dialog.py
asammdf/gui/dialogs/functions_manager.py
asammdf/gui/dialogs/gps_dialog.py
asammdf/gui/dialogs/messagebox.py
asammdf/gui/dialogs/multi_search.py
asammdf/gui/dialogs/range_editor.py
asammdf/gui/dialogs/window_selection_dialog.py
asammdf/gui/plot.py
asammdf/gui/serde.py
asammdf/gui/ui/__init__.py
asammdf/gui/ui/attachment.py
asammdf/gui/ui/attachment.ui
asammdf/gui/ui/bar.py
asammdf/gui/ui/bar.ui
asammdf/gui/ui/batch_widget.py
asammdf/gui/ui/batch_widget.ui
asammdf/gui/ui/bus_database_manager.py
asammdf/gui/ui/bus_database_manager.ui
asammdf/gui/ui/channel_bar_display_widget.py
asammdf/gui/ui/channel_bar_display_widget.ui
asammdf/gui/ui/channel_group_info_widget.py
asammdf/gui/ui/channel_group_info_widget.ui
asammdf/gui/ui/channel_info_widget.py
asammdf/gui/ui/channel_info_widget.ui
asammdf/gui/ui/channel_stats.py
asammdf/gui/ui/channel_stats.ui
asammdf/gui/ui/database_item.py
asammdf/gui/ui/database_item.ui
asammdf/gui/ui/define_channel_dialog.py
asammdf-8.7.1.dist-info/METADATA
asammdf-8.7.1.dist-info/WHEEL
asammdf-8.7.1.dist-info/entry_points.txt
asammdf-8.7.1.dist-info/licenses/LICENSE
asammdf-8.7.1.dist-info/RECORD
