Metadata-Version: 2.2
Name: asammdf
Version: 8.7.1
Summary: ASAM MDF measurement data file parser
Keywords: read,reader,edit,editor,parse,parser,asam,mdf,measurement
Author-Email: Daniel Hrisca <daniel.hrisca@gmail.com>
License: LGPLv3+
Classifier: Development Status :: 5 - Production/Stable
Classifier: Intended Audience :: Developers
Classifier: Topic :: Software Development
Classifier: Topic :: Scientific/Engineering
Classifier: License :: OSI Approved :: GNU Lesser General Public License v3 or later (LGPLv3+)
Classifier: Programming Language :: Python :: 3.10
Classifier: Programming Language :: Python :: 3.11
Classifier: Programming Language :: Python :: 3.12
Classifier: Programming Language :: Python :: 3.13
Classifier: Programming Language :: Python :: 3.14
Project-URL: Documentation, https://asammdf.readthedocs.io/en/master
Project-URL: Issues, https://github.com/danielhrisca/asammdf/issues
Project-URL: Source, https://github.com/danielhrisca/asammdf
Requires-Python: >=3.10
Requires-Dist: canmatrix[arxml,dbc]>=1.2
Requires-Dist: isal; platform_machine == "x86_64" or platform_machine == "AMD64"
Requires-Dist: lxml>=4.9.3
Requires-Dist: lz4
Requires-Dist: numexpr>=2.10.0
Requires-Dist: numpy>=2.0.0
Requires-Dist: pandas>=2.2.2
Requires-Dist: python-dateutil
Requires-Dist: typing-extensions~=4.10
Provides-Extra: decode
Requires-Dist: faust-cchardet==2.1.19; extra == "decode"
Requires-Dist: chardet; extra == "decode"
Provides-Extra: export
Requires-Dist: pyarrow>=17.0.0; extra == "export"
Requires-Dist: h5py>=3.11; extra == "export"
Requires-Dist: hdf5storage>=0.1.19; extra == "export"
Requires-Dist: python-snappy; extra == "export"
Requires-Dist: polars>=1.1.0; extra == "export"
Provides-Extra: export-matlab-v5
Requires-Dist: scipy>=1.13.0; extra == "export-matlab-v5"
Provides-Extra: gui
Requires-Dist: natsort; extra == "gui"
Requires-Dist: PySide6!=6.9.1,>=6.7.0; extra == "gui"
Requires-Dist: pyqtgraph>=0.13.4; extra == "gui"
Requires-Dist: pyqtlet2[PySide6]; extra == "gui"
Requires-Dist: packaging; extra == "gui"
Provides-Extra: encryption
Requires-Dist: cryptography; extra == "encryption"
Requires-Dist: keyring; extra == "encryption"
Provides-Extra: plot
Requires-Dist: matplotlib; extra == "plot"
Provides-Extra: symbolic-math
Requires-Dist: sympy>=1.13.0; extra == "symbolic-math"
Provides-Extra: filesystem
Requires-Dist: fsspec; extra == "filesystem"
